MANIFEST.in
README.rst
setup.py
django_nojs.egg-info/PKG-INFO
django_nojs.egg-info/SOURCES.txt
django_nojs.egg-info/dependency_links.txt
django_nojs.egg-info/not-zip-safe
django_nojs.egg-info/top_level.txt
nojs/__init__.py
nojs/models.py
nojs/urls.py
nojs/views.py
nojs/static/nojs/chrome.png
nojs/static/nojs/chromium.png
nojs/static/nojs/error.gif
nojs/static/nojs/ff.jpg
nojs/static/nojs/ie.gif
nojs/static/nojs/nojs.css
nojs/static/nojs/opera.jpg
nojs/static/nojs/safari.jpg
nojs/templates/index.html
nojs/templates/nojs/chrome.html
nojs/templates/nojs/chromium.html
nojs/templates/nojs/ff.html
nojs/templates/nojs/ie.html
nojs/templates/nojs/nojs.html
nojs/templates/nojs/opera.html
nojs/templates/nojs/safari.html
nojs/templates/nojs/unknown.html
nojs/templatetags/__init__.py
nojs/templatetags/nojs.py