Metadata-Version: 1.0
Name: django-nojs
Version: 0.0.1
Summary: UNKNOWN
Home-page: https://github.com/saxix/django-nojs
Author: sax
Author-email: sax@os4d.org
License: BSD
Platform: any
